snapcast/__init__.py
snapcast/client/__init__.py
snapcast/client/gstreamer.py
snapcast/client/messages.py
snapcast/control/__init__.py
snapcast/control/client.py
snapcast/control/group.py
snapcast/control/protocol.py
snapcast/control/server.py
snapcast/control/stream.py
snapcast_mod-2.4.6.dist-info/LICENSE
snapcast_mod-2.4.6.dist-info/METADATA
snapcast_mod-2.4.6.dist-info/WHEEL
snapcast_mod-2.4.6.dist-info/top_level.txt
snapcast_mod-2.4.6.dist-info/RECORD
