Metadata-Version: 2.1
Name: snapcast-mod
Version: 2.4.6
Summary: Control Snapcast.
Home-page: https://github.com/SantiagoSotoC/python-snapcast
Author: happyleaves
Author-email: happyleaves.tfr@gmail.com
License: MIT
Classifier: License :: OSI Approved :: MIT License
Classifier: Operating System :: OS Independent
Classifier: Programming Language :: Python :: 3
License-File: LICENSE
Requires-Dist: construct>=2.5.2
Requires-Dist: packaging
